LICENSE
README.md
ntc_templates/__init__.py
ntc_templates/parse.py
ntc_templates/templates/alcatel_aos_show_vlan.textfsm
ntc_templates/templates/alcatel_sros_oam_mac-ping.textfsm
ntc_templates/templates/alcatel_sros_ping.textfsm
ntc_templates/templates/alcatel_sros_show_lag.textfsm
ntc_templates/templates/alcatel_sros_show_port.textfsm
ntc_templates/templates/alcatel_sros_show_router_bgp_routes_vpn-ipv4.textfsm
ntc_templates/templates/alcatel_sros_show_router_bgp_summary_family.textfsm
ntc_templates/templates/alcatel_sros_show_router_interface.textfsm
ntc_templates/templates/alcatel_sros_show_router_isis_adjacency.textfsm
ntc_templates/templates/alcatel_sros_show_router_isis_interface.textfsm
ntc_templates/templates/alcatel_sros_show_router_ldp_interface.textfsm
ntc_templates/templates/alcatel_sros_show_router_mpls_interface.textfsm
ntc_templates/templates/alcatel_sros_show_router_mpls_lsp.textfsm
ntc_templates/templates/alcatel_sros_show_router_ospf_interface.textfsm
ntc_templates/templates/alcatel_sros_show_router_pim_interface.textfsm
ntc_templates/templates/alcatel_sros_show_router_rsvp_interface.textfsm
ntc_templates/templates/alcatel_sros_show_service_id_base.textfsm
ntc_templates/templates/alcatel_sros_show_service_id_interface.textfsm
ntc_templates/templates/alcatel_sros_show_service_sap-using.textfsm
ntc_templates/templates/alcatel_sros_show_service_sdp-using.textfsm
ntc_templates/templates/alcatel_sros_show_service_sdp.textfsm
ntc_templates/templates/alcatel_sros_show_system_cpu.textfsm
ntc_templates/templates/allied_telesis_awplus_show_arp.textfsm
ntc_templates/templates/allied_telesis_awplus_show_etherchannel_summary.textfsm
ntc_templates/templates/allied_telesis_awplus_show_interface.textfsm
ntc_templates/templates/allied_telesis_awplus_show_interface_switchport.textfsm
ntc_templates/templates/allied_telesis_awplus_show_ip_route.textfsm
ntc_templates/templates/allied_telesis_awplus_show_lldp_neighbors_detail.textfsm
ntc_templates-6.1.0.dist-info/LICENSE
ntc_templates-6.1.0.dist-info/METADATA
ntc_templates-6.1.0.dist-info/WHEEL
ntc_templates-6.1.0.dist-info/RECORD
